setup.py
pyrenew/__init__.py
pyrenew.egg-info/PKG-INFO
pyrenew.egg-info/SOURCES.txt
pyrenew.egg-info/dependency_links.txt
pyrenew.egg-info/requires.txt
pyrenew.egg-info/top_level.txt