Metadata-Version: 2.1
Name: pyrenew
Version: 0.0.2
Summary: Auto Updater
Author: r4isy
Author-email: r4isy@kenucorp.com
